logikal_docs/__init__.py
logikal_docs/__main__.py
logikal_docs/docs.py
logikal_docs/py.typed
logikal_docs/static/favicon.png
logikal_docs/static/favicon.svg
logikal_docs/static/css/logikal_docs.css
logikal_docs/static/css/fonts/RobotoMono-Bold.ttf
logikal_docs/static/css/fonts/RobotoMono-Bold.woff
logikal_docs/static/css/fonts/RobotoMono-Bold.woff2
logikal_docs/static/css/fonts/RobotoMono-BoldItalic.ttf
logikal_docs/static/css/fonts/RobotoMono-BoldItalic.woff
logikal_docs/static/css/fonts/RobotoMono-BoldItalic.woff2
logikal_docs/static/css/fonts/RobotoMono-Italic.ttf
logikal_docs/static/css/fonts/RobotoMono-Italic.woff
logikal_docs/static/css/fonts/RobotoMono-Italic.woff2
logikal_docs/static/css/fonts/RobotoMono-LICENSE.txt
logikal_docs/static/css/fonts/RobotoMono-Regular.ttf
logikal_docs/static/css/fonts/RobotoMono-Regular.woff
logikal_docs/static/css/fonts/RobotoMono-Regular.woff2
logikal_docs/templates/searchbox.html
logikal_docs/templates/versions.html
logikal_docs-1.2.4.dist-info/licenses/LICENSE.txt
logikal_docs-1.2.4.dist-info/METADATA
logikal_docs-1.2.4.dist-info/WHEEL
logikal_docs-1.2.4.dist-info/entry_points.txt
logikal_docs-1.2.4.dist-info/top_level.txt
logikal_docs-1.2.4.dist-info/RECORD
